crime/__init__.py
crime/crime.py
crime/library.py
crime/soda_api.py
crime-0.1.5.dist-info/METADATA
crime-0.1.5.dist-info/WHEEL
crime-0.1.5.dist-info/licenses/LICENSE
crime-0.1.5.dist-info/RECORD
