Metadata-Version: 2.1
Name: crime
Version: 0.1.5
Summary: Explore, load, and get documentation for Colorado crime data.
Project-URL: Documentation, https://github.com/ryayoung/crime
Project-URL: Website, https://colorado-crime.herokuapp.com/
Author-email: Ryan Young <dev@ryayoung.com>
Maintainer-email: Ryan Young <dev@ryayoung.com>
License: Copyright 2022 Ryan Young
License-File: LICENSE
Keywords: colorado crime,open data api,open data network,socrata
Classifier: License :: OSI Approved :: MIT License
Classifier: Operating System :: OS Independent
Classifier: Programming Language :: Python :: 3.9
Requires-Python: >=3.9
Requires-Dist: pandas
Requires-Dist: requests
Requires-Dist: sodapy
